jaraco/pmxbot/__init__.py
jaraco/pmxbot/notification.py
jaraco.pmxbot-6.2.0.dist-info/LICENSE
jaraco.pmxbot-6.2.0.dist-info/METADATA
jaraco.pmxbot-6.2.0.dist-info/WHEEL
jaraco.pmxbot-6.2.0.dist-info/entry_points.txt
jaraco.pmxbot-6.2.0.dist-info/top_level.txt
jaraco.pmxbot-6.2.0.dist-info/RECORD
